chandler/configuration.py
chandler/utils.py
chandler/main.py
chandler/__init__.py
chandler/default_chandler.conf
chandler-0.1.0.dist-info/top_level.txt
chandler-0.1.0.dist-info/entry_points.txt
chandler-0.1.0.dist-info/METADATA
chandler-0.1.0.dist-info/DESCRIPTION.rst
chandler-0.1.0.dist-info/metadata.json
chandler-0.1.0.dist-info/WHEEL
chandler-0.1.0.dist-info/RECORD
